pygardena/__init__.py
pygardena/const.py
tests/__init__.py
tests/test_rest.py
pygardena-0.7.1.dist-info/LICENSE
pygardena-0.7.1.dist-info/METADATA
pygardena-0.7.1.dist-info/WHEEL
pygardena-0.7.1.dist-info/top_level.txt
pygardena-0.7.1.dist-info/RECORD
