Metadata-Version: 2.1
Name: pygardena
Version: 0.7.1
Summary: Library to communicate with Gardena smart home products
Home-page: https://github.com/liquid667/pygardena
Author: Mikael Johansson
Author-email: mikael@thematrix.se
License: Apache License
